expiration_manager/__init__.py
expiration_manager/db.py
expiration_manager/logger.py
expiration_manager/manager.py
neojelll_url_shortener_expiration_manager-0.1.30.dist-info/METADATA
neojelll_url_shortener_expiration_manager-0.1.30.dist-info/WHEEL
neojelll_url_shortener_expiration_manager-0.1.30.dist-info/entry_points.txt
neojelll_url_shortener_expiration_manager-0.1.30.dist-info/RECORD
