Metadata-Version: 2.1
Name: neojelll-url-shortener-expiration-manager
Version: 0.1.30
Summary: 
Author: neojelll
Author-email: timofejmitusin60892@gmail.com
Requires-Python: >=3.12,<4.0
Classifier: Programming Language :: Python :: 3
Classifier: Programming Language :: Python :: 3.12
Classifier: Programming Language :: Python :: 3.13
Requires-Dist: asyncpg (>=0.29.0,<0.30.0)
Requires-Dist: loguru (>=0.7.2,<0.8.0)
Requires-Dist: python-dotenv (>=1.0.1,<2.0.0)
Requires-Dist: sqlalchemy[asyncio] (>=2.0.35,<3.0.0)
